.version
MANIFEST.in
README.md
setup.cfg
setup.py
bin/pysshchat
pySSHChat.egg-info/PKG-INFO
pySSHChat.egg-info/SOURCES.txt
pySSHChat.egg-info/dependency_links.txt
pySSHChat.egg-info/requires.txt
pySSHChat.egg-info/top_level.txt
pysshchat/.version
pysshchat/__init__.py
pysshchat/__main__.py
pysshchat/libs.py
pysshchat/server.py
pysshchat/store.py
pysshchat/__pycache__/__init__.cpython-35.pyc
pysshchat/__pycache__/__main__.cpython-35.pyc
pysshchat/__pycache__/version.cpython-35.pyc
pysshchat/commands/__init__.py
pysshchat/commands/admin.py
pysshchat/commands/crypto.py
pysshchat/commands/default.py
pysshchat/commands/__pycache__/default.cpython-35.pyc
pysshchat/lib/__pycache__/__init__.cpython-35.pyc
pysshchat/lib/__pycache__/host_key.cpython-35.pyc
pysshchat/lib/__pycache__/keycode.cpython-35.pyc
pysshchat/user/__init__.py
pysshchat/user/line/__init__.py
pysshchat/user/ui/__init__.py
pysshchat/user/ui/alert.py
pysshchat/user/ui/chat.py
pysshchat/user/ui/palette.py
pysshchat/user/ui/screen.py
pysshchat/yaml/config.yaml
pysshchat/yaml/texts.yaml