Metadata-Version: 1.0
Name: pySSHChat
Version: 2.1.22
Summary: SSH chat server written on Python3
Home-page: https://github.com/LexSerest/pySSHChat/
Author: LexSerest
Author-email: lexserest@gmail.com
License: MIT
Keywords: ssh,chat,ssh chat
Platform: UNKNOWN
